{
  "Past Speaking Engagements": [
    {
      "title": "AI Ethics and Governance in the Digital Era",
      "event": "2024 International Forum on Technology and Society",
      "location": "Taipei, Taiwan",
      "year": 2024,
      "description": "Delivered a keynote address on ethical frameworks for artificial intelligence policy in East Asia."
    },
    {
      "title": "Political Polarization and Social Media Algorithms",
      "event": "Asia-Pacific Conference on Political Communication",
      "location": "Seoul, South Korea",
      "year": 2023,
      "description": "Presented empirical research on algorithmic personalization and its effects on public discourse."
    },
    {
      "title": "Civic Participation in the Post-Pandemic World",
      "event": "International Symposium on Digital Democracy",
      "location": "Tokyo, Japan",
      "year": 2022,
      "description": "Discussed the role of digital platforms in shaping public engagement after COVID-19."
    }
  ]
}
